worker_dispatcher/__init__.py
worker_dispatcher/worker_dispatcher.py
worker_dispatcher-1.3.1.dist-info/METADATA
worker_dispatcher-1.3.1.dist-info/WHEEL
worker_dispatcher-1.3.1.dist-info/licenses/LICENSE
worker_dispatcher-1.3.1.dist-info/RECORD
