Metadata-Version: 2.4
Name: worker_dispatcher
Version: 1.3.1
Summary: A flexible task dispatcher for Python with multiple threading or processing control
Project-URL: Homepage, https://github.com/yidas/python-worker-dispatcher
Project-URL: Issues, https://github.com/yidas/python-worker-dispatcher/issues
Author-email: Nick Tsai <myintaer@gmail.com>
License-File: LICENSE
Classifier: License :: OSI Approved :: MIT License
Classifier: Operating System :: OS Independent
Classifier: Programming Language :: Python :: 3
Requires-Python: >=3.0
Requires-Dist: requests>=2.0.0
